<xml xmlns="http://www.w3.org/1999/xhtml">
  <variables>
    <variable type="" id="C6;Y;!Ug$~FFgA5vxkh5">Path-of-a-Free-Particle</variable>
    <variable type="" id="mF)O/+nOapCq.R.17pea">time</variable>
    <variable type="" id="I;wVaDp!y]/||%yY8]!5">Kinetic-Energy</variable>
    <variable type="" id="#MMO]F{w@;+?h|h:V|6}">velocity</variable>
    <variable type="" id="Ro|zq4z^bW2c!^_K#T!L">Lagrangian</variable>
    <variable type="" id="pXYN4M[Ty#cKwhe`]8==">position</variable>
  </variables>
  <shadow type="idfuns-v-3" id="L~2VJ4@ua^[%@3l4SFNk" x="16" y="-50">
    <field name="vegatex">print-text</field>
    <field name="id">The Free</field>
    <value name="args-3">
      <shadow type="text" id="owR8r?1h_+iV|5,s9Gec">
        <field name="dertext">Particle</field>
      </shadow>
    </value>
  </shadow>
  <shadow type="funs-v-4-defn" id="h5A0*J7T[e6rPu(e18]q" x="16" y="-9">
    <field name="funsnamen">defn</field>
    <value name="args-2">
      <shadow type="variables_get" id=",KBtB.;Oe;,p.gm1nQDf">
        <field name="VAR" id="C6;Y;!Ug$~FFgA5vxkh5" variabletype="">Path-of-a-Free-Particle</field>
      </shadow>
    </value>
    <value name="args-3">
      <shadow type="variables_get" id="XhmX,+4SLw9s@XW^R,{N">
        <field name="VAR" id="mF)O/+nOapCq.R.17pea" variabletype="">time</field>
      </shadow>
    </value>
    <value name="args-4">
      <shadow type="funs-v-3" id="3@-uV5]]46w*@Iv2e@@0">
        <field name="funsnamen">up</field>
        <value name="args-2">
          <shadow type="funs-h-3" id="G(9@s(SQ%$ap25w}:]$S">
            <field name="funsnamen">+</field>
            <value name="args-2">
              <shadow type="funs-h-3" id="Mx;Xjv8TGNOldA{`!DIZ">
                <field name="funsnamen">*</field>
                <value name="args-2">
                  <shadow type="num" id="DZfH:HJ!Gkm1*;HEs#w0">
                    <field name="nummer">5</field>
                  </shadow>
                </value>
                <value name="args-3">
                  <shadow type="variables_get" id="et=*ew|=kp@ACXjC5k=a">
                    <field name="VAR" id="mF)O/+nOapCq.R.17pea" variabletype="">time</field>
                  </shadow>
                </value>
              </shadow>
            </value>
            <value name="args-3">
              <shadow type="num" id="?3lR7mt~`gT,zumi5`m9">
                <field name="nummer">2</field>
              </shadow>
            </value>
          </shadow>
        </value>
        <value name="args-3">
          <shadow type="funs-h-3" id="B0m-h?2FxZmmSgVr!(42">
            <field name="funsnamen">+</field>
            <value name="args-2">
              <shadow type="funs-h-3" id="Z43d+QmZPB0Dk(J:AJN8">
                <field name="funsnamen">*</field>
                <value name="args-2">
                  <shadow type="num" id="6E;eZ[La,z=UteaV.vom">
                    <field name="nummer">4</field>
                  </shadow>
                </value>
                <value name="args-3">
                  <shadow type="variables_get" id="m;4[Nsx(3]@B(]~`BZJ`">
                    <field name="VAR" id="mF)O/+nOapCq.R.17pea" variabletype="">time</field>
                  </shadow>
                </value>
              </shadow>
            </value>
            <value name="args-3">
              <shadow type="num" id="|vXOF{32Oy_L6_o{cJp)">
                <field name="nummer">3</field>
              </shadow>
            </value>
          </shadow>
        </value>
      </shadow>
    </value>
  </shadow>
  <shadow type="funs-v-4-defn" id="9W8|-#v0DVEbn4]A650." x="17" y="143">
    <field name="funsnamen">defn</field>
    <value name="args-2">
      <shadow type="variables_get" id="mr25uGr1a|h$cTwqP*3y">
        <field name="VAR" id="I;wVaDp!y]/||%yY8]!5" variabletype="">Kinetic-Energy</field>
      </shadow>
    </value>
    <value name="args-3">
      <shadow type="variables_get" id="a]2)$!?J8UaQ~wghdk6_">
        <field name="VAR" id="#MMO]F{w@;+?h|h:V|6}" variabletype="">velocity</field>
      </shadow>
    </value>
    <value name="args-4">
      <shadow type="funs-h-2" id="DM6])A=~?$4/{gR~HR{~">
        <field name="funsnamen">square</field>
        <value name="args-2">
          <shadow type="variables_get" id="pArDM8vSn^FPN~u:BUP,">
            <field name="VAR" id="#MMO]F{w@;+?h|h:V|6}" variabletype="">velocity</field>
          </shadow>
        </value>
      </shadow>
    </value>
  </shadow>
  <block type="idfuns-v-3" id="`xC]VyZNT3t3T3C[S@/j" x="-450" y="195">
    <field name="vegatex">tex</field>
    <field name="id">x(t) =</field>
    <value name="args-3">
      <block type="funs-h-2-cus" id="LT$%2tBcd?{?jn:PNJwT">
        <field name="kopf" id="C6;Y;!Ug$~FFgA5vxkh5" variabletype="">Path-of-a-Free-Particle</field>
        <value name="args-2">
          <block type="num_sym" id="hq%y,y,%M34.vf8+Q+8]">
            <field name="nummer">'t</field>
          </block>
        </value>
      </block>
    </value>
  </block>
  <shadow type="idfuns-v-3" id="vvF-m{})a_3`AlBUHiWs" x="16" y="235">
    <field name="vegatex">tex</field>
    <field name="id">x(t) =</field>
    <value name="args-3">
      <shadow type="funs-h-2-cus" id="V],~HFL[v|uSSdfT(qk8">
        <field name="kopf" id="C6;Y;!Ug$~FFgA5vxkh5" variabletype="">Path-of-a-Free-Particle</field>
        <value name="args-2">
          <shadow type="num_sym" id="Rv`f|A%f#VL5]K{{r7%E">
            <field name="nummer">'t</field>
          </shadow>
        </value>
      </shadow>
    </value>
  </shadow>
  <shadow type="idfuns-v-3" id="$g6f6c^[o)}7IbIa]^@)" x="16" y="288">
    <field name="vegatex">tex</field>
    <field name="id">K(v) =</field>
    <value name="args-3">
      <shadow type="funs-h-2-cus" id="k_Ta4hR7YhVV^2YM=]3c">
        <field name="kopf" id="I;wVaDp!y]/||%yY8]!5" variabletype="">Kinetic-Energy</field>
        <value name="args-2">
          <shadow type="num_sym" id="dF[fSTn}q)#1ap-kX?wU">
            <field name="nummer">'v</field>
          </shadow>
        </value>
      </shadow>
    </value>
  </shadow>
  <shadow type="funs-v-4-defn" id="w4*@.:xE;B|oO+V4u1hj" x="16" y="354">
    <field name="funsnamen">defn</field>
    <value name="args-2">
      <shadow type="variables_get" id="7!Xv3scM~^[SWVf)QSid">
        <field name="VAR" id="Ro|zq4z^bW2c!^_K#T!L" variabletype="">Lagrangian</field>
      </shadow>
    </value>
    <value name="args-3">
      <shadow type="args-1" id="g[G@:]3c]t1${}rFwX)z">
        <value name="arg_1">
          <shadow type="args-3" id="IMMO0ppYl$9Bitw^S3+F">
            <value name="arg_1">
              <shadow type="variables_get" id="p[lX-u%s{_?V1Zb,3Ar%">
                <field name="VAR" id="mF)O/+nOapCq.R.17pea" variabletype="">time</field>
              </shadow>
            </value>
            <value name="arg_2">
              <shadow type="variables_get" id="VE6JSjl=l*l8duo7##y7">
                <field name="VAR" id="pXYN4M[Ty#cKwhe`]8==" variabletype="">position</field>
              </shadow>
            </value>
            <value name="arg_3">
              <shadow type="variables_get" id="VSD[q5Xmb=FF=Ez1]?0T">
                <field name="VAR" id="#MMO]F{w@;+?h|h:V|6}" variabletype="">velocity</field>
              </shadow>
            </value>
          </shadow>
        </value>
      </shadow>
    </value>
    <value name="args-4">
      <shadow type="funs-h-2-cus" id="|gnz:c$A*7q*caqSauhs">
        <field name="kopf" id="I;wVaDp!y]/||%yY8]!5" variabletype="">Kinetic-Energy</field>
        <value name="args-2">
          <shadow type="variables_get" id="2fd;[`L});drGf$ue*xT">
            <field name="VAR" id="#MMO]F{w@;+?h|h:V|6}" variabletype="">velocity</field>
          </shadow>
        </value>
      </shadow>
    </value>
  </shadow>
</xml>